pywrapgeneid/__init__.py
pywrapgeneid/geneid.py
pywrapgeneid/predict_geneid.py
pywrapgeneid-1.2.dist-info/METADATA
pywrapgeneid-1.2.dist-info/WHEEL
pywrapgeneid-1.2.dist-info/top_level.txt
pywrapgeneid-1.2.dist-info/RECORD
