Metadata-Version: 2.1
Name: pywrapgeneid
Version: 1.2
Summary: Python wrapper for geneid program
Author: Danish Aslam
Author-email: danish2101125@st.jmi.ac.in
